gtfparse/__init__.py
gtfparse/attribute_parsing.py
gtfparse/create_missing_features.py
gtfparse/parsing_error.py
gtfparse/read_gtf.py
gtfparse_transcript_transformer-2.5.0.dist-info/licenses/LICENSE
gtfparse_transcript_transformer-2.5.0.dist-info/METADATA
gtfparse_transcript_transformer-2.5.0.dist-info/WHEEL
gtfparse_transcript_transformer-2.5.0.dist-info/top_level.txt
gtfparse_transcript_transformer-2.5.0.dist-info/RECORD
