Metadata-Version: 2.4
Name: gtfparse_transcript_transformer
Version: 2.5.0
Summary: Parsing library for extracting data frames of genomic features from GTF files
Author-email: Alex Rubinsteyn <alex.rubinsteyn@unc.edu>
Project-URL: Homepage, https://github.com/jdcla/gtfparse
Project-URL: Bug Tracker, https://github.com/jdcla/gtfparse
Classifier: Development Status :: 4 - Beta
Classifier: Environment :: Console
Classifier: Operating System :: OS Independent
Classifier: Intended Audience :: Science/Research
Classifier: License :: OSI Approved :: Apache Software License
Classifier: Programming Language :: Python
Classifier: Topic :: Scientific/Engineering :: Bio-Informatics
Requires-Python: >=3.7
License-File: LICENSE
Requires-Dist: polars>=0.20.2
Requires-Dist: pyarrow>=15
Requires-Dist: pandas>=2.1.0
Dynamic: license-file
